LICENSE
README.md
setup.py
src/cit_keri.egg-info/PKG-INFO
src/cit_keri.egg-info/SOURCES.txt
src/cit_keri.egg-info/dependency_links.txt
src/cit_keri.egg-info/entry_points.txt
src/cit_keri.egg-info/not-zip-safe
src/cit_keri.egg-info/requires.txt
src/cit_keri.egg-info/top_level.txt
src/keri/__init__.py
src/keri/kering.py
src/keri/app/__init__.py
src/keri/app/agenting.py
src/keri/app/apping.py
src/keri/app/challenging.py
src/keri/app/configing.py
src/keri/app/connecting.py
src/keri/app/delegating.py
src/keri/app/directing.py
src/keri/app/forwarding.py
src/keri/app/grouping.py
src/keri/app/habbing.py
src/keri/app/httping.py
src/keri/app/indirecting.py
src/keri/app/keeping.py
src/keri/app/notifying.py
src/keri/app/oobiing.py
src/keri/app/querying.py
src/keri/app/signaling.py
src/keri/app/signing.py
src/keri/app/specing.py
src/keri/app/storing.py
src/keri/app/watching.py
src/keri/app/cli/__init__.py
src/keri/app/cli/kli.py
src/keri/app/cli/commands/__init__.py
src/keri/app/cli/commands/aid.py
src/keri/app/cli/commands/clean.py
src/keri/app/cli/commands/decrypt.py
src/keri/app/cli/commands/escrow.py
src/keri/app/cli/commands/event.py
src/keri/app/cli/commands/export.py
src/keri/app/cli/commands/incept.py
src/keri/app/cli/commands/init.py
src/keri/app/cli/commands/interact.py
src/keri/app/cli/commands/introduce.py
src/keri/app/cli/commands/kevers.py
src/keri/app/cli/commands/list.py
src/keri/app/cli/commands/nonce.py
src/keri/app/cli/commands/query.py
src/keri/app/cli/commands/rename.py
src/keri/app/cli/commands/rollback.py
src/keri/app/cli/commands/rotate.py
src/keri/app/cli/commands/saidify.py
src/keri/app/cli/commands/salt.py
src/keri/app/cli/commands/sign.py
src/keri/app/cli/commands/status.py
src/keri/app/cli/commands/time.py
src/keri/app/cli/commands/verify.py
src/keri/app/cli/commands/version.py
src/keri/app/cli/commands/challenge/__init__.py
src/keri/app/cli/commands/challenge/generate.py
src/keri/app/cli/commands/challenge/respond.py
src/keri/app/cli/commands/challenge/verify.py
src/keri/app/cli/commands/contacts/__init__.py
src/keri/app/cli/commands/contacts/list.py
src/keri/app/cli/commands/delegate/__init__.py
src/keri/app/cli/commands/delegate/confirm.py
src/keri/app/cli/commands/delegate/request.py
