Metadata-Version: 2.1
Name: cit-keri
Version: 1.2.8
Summary: Key Event Receipt Infrastructure
Home-page: https://github.com/WebOfTrust/keripy
Author: Samuel M. Smith
Author-email: smith.samuel.m@gmail.com
License: Apache Software License 2.0
Project-URL: Documentation, https://keri.readthedocs.io/
Project-URL: Changelog, https://keri.readthedocs.io/en/latest/changelog.html
Project-URL: Issue Tracker, https://github.com/WebOfTrust/keripy/issues
Classifier: Development Status :: 3 - Alpha
Classifier: Intended Audience :: Developers
Classifier: License :: OSI Approved :: Apache Software License
Classifier: Operating System :: Unix
Classifier: Operating System :: POSIX
Classifier: Operating System :: Microsoft :: Windows
Classifier: Programming Language :: Python :: 3.12
Classifier: Programming Language :: Python :: Implementation :: CPython
Classifier: Topic :: Utilities
Requires-Python: >=3.12.2
License-File: LICENSE
Requires-Dist: lmdb>=1.4.1
Requires-Dist: pysodium>=0.7.17
Requires-Dist: blake3>=0.4.1
Requires-Dist: msgpack>=1.0.8
Requires-Dist: cbor2>=5.6.2
Requires-Dist: multidict>=6.0.5
Requires-Dist: ordered-set>=4.1.0
Requires-Dist: hio==0.6.14
Requires-Dist: multicommand>=1.0.0
Requires-Dist: jsonschema>=4.21.1
Requires-Dist: falcon>=3.1.3
Requires-Dist: hjson>=3.1.0
Requires-Dist: PyYaml>=6.0.1
Requires-Dist: apispec>=6.6.0
Requires-Dist: mnemonic>=0.21
Requires-Dist: PrettyTable>=3.10.0
Requires-Dist: http_sfv>=0.9.9
Requires-Dist: cryptography>=42.0.5
Requires-Dist: semver>=3.0.2
Requires-Dist: qrcode>=7.4.2
